__init__.py
main.py
m_shape/__init__.py
m_shape/detectFacialFeatures.py
m_shape/predict.py
m_shape/utilities/__init__.py
m_shape/utilities/algorithm_utils.py
m_shape/utilities/drawAndCalculate.py
m_shape/utilities/preprocess.py
m_shape/utilities/print_utils.py
m_shape/utilities/shape_predictor_68_face_landmarks.dat
m_shape/utilities/shape_predictor_81_face_landmarks.dat
requirements/__init__.py
requirements/requirements.txt
sample_images/__init__.py
M_Shape_Head_Package-0.0.6.post6.dist-info/LICENSE
M_Shape_Head_Package-0.0.6.post6.dist-info/METADATA
M_Shape_Head_Package-0.0.6.post6.dist-info/WHEEL
M_Shape_Head_Package-0.0.6.post6.dist-info/top_level.txt
M_Shape_Head_Package-0.0.6.post6.dist-info/RECORD
